{
    "total": [
        {
            "id": "61551447209480",
            "count": 0
        },
        {
            "id": "100040472494187",
            "count": 12
        },
        {
            "id": "100067848937650",
            "count": 0
        }
    ],
    "week": [
        {
            "id": "61551447209480",
            "count": 0
        },
        {
            "id": "100040472494187",
            "count": 12
        },
        {
            "id": "100067848937650",
            "count": 0
        }
    ],
    "day": [
        {
            "id": "61551447209480",
            "count": 0,
            "name": "️️️️️️️️️️️️️️️️️️️️️️️️️️️️️️️️️️️️️️️️️️️️️️️️️️️️️️️️️️️️️️️️️️️️️️️️️️️️️️️️️️️️️️️️️️️️️️️️️️️️️️️️️️️️️️️️️️️️️️️️️️️️️️️️️️️️️️️️️️️️️️️️️️️️️️️️️️️️️️️️️️️️️️️️️️"
        },
        {
            "id": "100040472494187",
            "count": 0,
            "name": "Nguyễn Tuấn Ninh"
        },
        {
            "id": "100067848937650",
            "count": 0,
            "name": "Đùakhôngvui Taođãcăng"
        }
    ],
    "time": 0
}